{
    "login":  {
                  "page":  {
                               "background_type":  "color",
                               "background_color":  "#fafafa"
                           },
                  "logo":  {
                               "type":  "hide"
                           },
                  "form":  {
                               "background_color":  "#ffffff",
                               "border_radius":  0,
                               "width":  340
                           },
                  "heading":  {
                                  "show":  true,
                                  "text":  "Login",
                                  "color":  "#222222"
                              },
                  "fields":  {
                                 "border_color":  "#e0e0e0",
                                 "border_radius":  0
                             },
                  "button":  {
                                 "background_color":  "#222222",
                                 "text_color":  "#ffffff",
                                 "border_radius":  0
                             },
                  "links":  {
                                "color":  "#888888",
                                "show_lost_password":  false
                            }
              },
    "register":  {
                     "page":  {
                                  "background_type":  "color",
                                  "background_color":  "#fafafa"
                              },
                     "logo":  {
                                  "type":  "hide"
                              },
                     "form":  {
                                  "background_color":  "#ffffff",
                                  "border_radius":  0,
                                  "width":  340
                              },
                     "heading":  {
                                     "show":  true,
                                     "text":  "Login",
                                     "color":  "#222222"
                                 },
                     "fields":  {
                                    "border_color":  "#e0e0e0",
                                    "border_radius":  0
                                },
                     "button":  {
                                    "background_color":  "#222222",
                                    "text_color":  "#ffffff",
                                    "border_radius":  0
                                },
                     "links":  {
                                   "color":  "#888888",
                                   "show_lost_password":  false
                               }
                 },
    "lostpassword":  {
                         "page":  {
                                      "background_type":  "color",
                                      "background_color":  "#fafafa"
                                  },
                         "logo":  {
                                      "type":  "hide"
                                  },
                         "form":  {
                                      "background_color":  "#ffffff",
                                      "border_radius":  0,
                                      "width":  340
                                  },
                         "heading":  {
                                         "show":  true,
                                         "text":  "Login",
                                         "color":  "#222222"
                                     },
                         "fields":  {
                                        "border_color":  "#e0e0e0",
                                        "border_radius":  0
                                    },
                         "button":  {
                                        "background_color":  "#222222",
                                        "text_color":  "#ffffff",
                                        "border_radius":  0
                                    },
                         "links":  {
                                       "color":  "#888888",
                                       "show_lost_password":  false
                                   }
                     },
    "password":  {
                     "show_top_text":  "on",
                     "top_header":  "Protected",
                     "top_content":  "",
                     "top_text_align":  "center",
                     "form_label":  "Password",
                     "form_btn_text":  "Go",
                     "form_background":  "transparent",
                     "form_border_radius":  0,
                     "show_social":  "off",
                     "show_bottom_text":  "off",
                     "form_text_color":  "#ffffff",
                     "page_background_color":  "#f5f5f5",
                     "button_border_radius":  0,
                     "heading_color":  "#ffffff",
                     "active_style":  "three",
                     "page_background_type":  "color",
                     "label_color":  "#e0e0e0",
                     "button_color":  "#1a1a1a",
                     "button_text_color":  "#ffffff"
                 }
}